python_tsl2591/__init__.py
python_tsl2591/__version__.py
python_tsl2591/sensor.py
python_tsl2591-0.2.0.dist-info/LICENSE
python_tsl2591-0.2.0.dist-info/METADATA
python_tsl2591-0.2.0.dist-info/WHEEL
python_tsl2591-0.2.0.dist-info/top_level.txt
python_tsl2591-0.2.0.dist-info/RECORD
