Metadata-Version: 2.1
Name: python-tsl2591
Version: 0.2.0
Summary: Community-coded Python module for TSL2591 sensor converted from Adafruit's TSL2591 library. Use at your own risk.
Home-page: http://github.com/kyletaylored/python-tsl2591
Author: Max Hofbauer
Author-email: maxhofb@gmail.com
License: MIT license
Keywords: python_tsl2591,tsl2591,light sensor,adafruit
Platform: UNKNOWN
Classifier: Development Status :: 2 - Pre-Alpha
Classifier: Intended Audience :: Developers
Classifier: License :: OSI Approved :: MIT License
Classifier: Natural Language :: English
Classifier: Programming Language :: Python :: 2
Classifier: Programming Language :: Python :: 2.7
Classifier: Programming Language :: Python :: 3
Classifier: Programming Language :: Python :: 3.4
Classifier: Programming Language :: Python :: 3.5
Classifier: Programming Language :: Python :: 3.6
Classifier: Programming Language :: Python :: 3.7
Classifier: Operating System :: POSIX :: Linux
